abelian/__init__.py
abelian/functions.py
abelian/groups.py
abelian/morphisms.py
abelian/utils.py
abelian/linalg/__init__.py
abelian/linalg/factorizations.py
abelian/linalg/factorizations_reals.py
abelian/linalg/free_to_free.py
abelian/linalg/solvers.py
abelian/linalg/utils.py
abelian-1.0.1.dist-info/DESCRIPTION.rst
abelian-1.0.1.dist-info/METADATA
abelian-1.0.1.dist-info/RECORD
abelian-1.0.1.dist-info/WHEEL
abelian-1.0.1.dist-info/metadata.json
abelian-1.0.1.dist-info/top_level.txt
