Metadata-Version: 2.0
Name: abelian
Version: 1.0.1
Summary: Computations on abelian groups.
Home-page: https://github.com/tommyod/abelian/
Author: Tommy Odland
Author-email: tommy.odland@student.uib.no
License: UNKNOWN
Platform: UNKNOWN
